[{"category":null,"questionTitle":"Her uncle is a doctor, isn't ___?","anwers":["he","she","it"],"correctAnswer":0},{"category":null,"questionTitle":"That old woman is kind to ___.","anwers":["our","we","us"],"correctAnswer":2},{"category":null,"questionTitle":"My car is new, but ___ is old.","anwers":["he's","his","him"],"correctAnswer":1},{"category":null,"questionTitle":"___ school is in the mountains.","anwers":["our","we","us"],"correctAnswer":0},{"category":null,"questionTitle":"The bird sang ___ happy tune.","anwers":["it","it's","its"],"correctAnswer":0},{"category":null,"questionTitle":"She has an apple in ___ hand.","anwers":["she","her","hers"],"correctAnswer":1},{"category":null,"questionTitle":"I gave ___ my pencil.","anwers":["he","his","him"],"correctAnswer":2},{"category":null,"questionTitle":"We are glad that you could stay with ___.","anwers":["our","we","us"],"correctAnswer":2},{"category":null,"questionTitle":"Do you have a dictionary? Yes, I have a good ___.","anwers":["some","another","one"],"correctAnswer":2},{"category":null,"questionTitle":"William and Tracy love ___ dog.","anwers":["they","them","their"],"correctAnswer":2}]