[{"category":null,"questionTitle":"This girl is ............................... than that one.","anwers":["as beautiful","the most beautiful","more beautiful","most beautiful"],"correctAnswer":2},{"category":null,"questionTitle":"John is ............................... student.","anwers":["a good","better","a worse","a best"],"correctAnswer":0},{"category":null,"questionTitle":"That exercise is ...................... long for that small boy to do in half an hour.","anwers":["very","not","too","so"],"correctAnswer":2},{"category":null,"questionTitle":"\"She used to play the piano\" means that .................................","anwers":["She plays the piano quite often","She played the piano now and then","She often played the piano in the past","She plays the piano occasionally"],"correctAnswer":2},{"category":null,"questionTitle":"A .................. is someone aged between 13 and 19.","anwers":["teenager","youth","graduate","student"],"correctAnswer":0},{"category":null,"questionTitle":"You can cut an orange with a ..............","anwers":["car","cup","knife","frying pan"],"correctAnswer":2},{"category":null,"questionTitle":"Without ............., you can't see anything.","anwers":["hands","ears","eyes","nose"],"correctAnswer":2},{"category":null,"questionTitle":"The pupils walked on the ...........................","anwers":["stair","pavement","train","river"],"correctAnswer":1},{"category":null,"questionTitle":"\"................ the time?\" \"It's half past eleven.\"","anwers":["When is","What's","Is it","We know"],"correctAnswer":1},{"category":null,"questionTitle":"\"Peter is twenty years old.\" \"............. is his younger sister?\" \"Thirteen years.\"","anwers":["Mrs. Black","Who","What","And how old"],"correctAnswer":3},{"category":null,"questionTitle":", can you tell me the way to the post office?","anwers":["Thank you","All right","Listen","Excuse me"],"correctAnswer":3},{"category":null,"questionTitle":"that street and the Odeon theater is at the next corner.","anwers":["Go along","Turn right","On the left of","Turn on"],"correctAnswer":0},{"category":null,"questionTitle":"In the big city everybody seemed to be ...........................","anwers":["hurry","a hurry","in a hurry","hurried"],"correctAnswer":2},{"category":null,"questionTitle":"She intends to ........................... for her mother at a bus stop.","anwers":["waiting","wait","waited","waits"],"correctAnswer":1},{"category":null,"questionTitle":"Life in a big city is always ...........................","anwers":["crowded","busy","lovely","happy"],"correctAnswer":1},{"category":null,"questionTitle":"She rewarded me with a bicycle ........................... my result.","anwers":["on","in","about","for"],"correctAnswer":3},{"category":null,"questionTitle":"Mary is having a look ........................... her friend's skirt.","anwers":["on","in","at","by"],"correctAnswer":2},{"category":null,"questionTitle":"He is a curious boy. He always .......... questions.","anwers":["asks","looks at","says","laughs at"],"correctAnswer":0},{"category":null,"questionTitle":"do you go to the library? Twice a week.","anwers":["How often","How","How long","How far"],"correctAnswer":0},{"category":null,"questionTitle":"Did they walk or come ............. car?","anwers":["with","in","by","through"],"correctAnswer":2},{"category":null,"questionTitle":"Nam went to the party last night but Dung ..................","anwers":["isn't","hasn't","didn't","wasn't"],"correctAnswer":2}]