[{"category":null,"questionTitle":"Is the tall man ________ husband?","anwers":["your sisters'","your sister's","your sister","your sister his"],"correctAnswer":1},{"category":null,"questionTitle":"This is a photo ________ my dog.","anwers":["about","from","by","of"],"correctAnswer":3},{"category":null,"questionTitle":"Have ________ had something to eat?","anwers":["them all","their all","all they","they all"],"correctAnswer":3},{"category":null,"questionTitle":"Please go and ________ a bath.","anwers":["wash","make","have","do"],"correctAnswer":2},{"category":null,"questionTitle":"The boys left ________ school before lunch.","anwers":["in the","-","out of","at"],"correctAnswer":1},{"category":null,"questionTitle":"There are three men ________ waiting outside.","anwers":["who","they","which","-"],"correctAnswer":3},{"category":null,"questionTitle":"Do you know these people? No, I don't know ________.","anwers":["they","their","them","their's"],"correctAnswer":2},{"category":null,"questionTitle":"The girls are ________ the discotheque.","anwers":["by","on","to","at"],"correctAnswer":3},{"category":null,"questionTitle":"________ you ride a motorbike?","anwers":["Have","Has","Can","How"],"correctAnswer":2},{"category":null,"questionTitle":"Just a moment. I'm putting you ________.","anwers":["up","under","through","in"],"correctAnswer":2},{"category":null,"questionTitle":"He will not be ________ to vote in this year's election.","anwers":["old enough","as old enough","enough old","enough old as"],"correctAnswer":0},{"category":null,"questionTitle":"It is not very easy to study a foreign language all by ________.","anwers":["oneself","itself","himself","herself"],"correctAnswer":0},{"category":null,"questionTitle":"You can ________ my surprise when I heard the news.","anwers":["suppose","think","see","imagine"],"correctAnswer":3},{"category":null,"questionTitle":"He ________ book the tickets, but he had no time to call at the cinem","anwers":["would","might","could","was going to"],"correctAnswer":3},{"category":null,"questionTitle":"A taxi collided with his car ten minutes ago but the police ________.","anwers":["has not come yet","have not come yet","did not come yet","don't come"],"correctAnswer":1},{"category":null,"questionTitle":"Her hands were so cold ________ she could not type.","anwers":["for","that","as","zero"],"correctAnswer":1},{"category":null,"questionTitle":"I want some sugar, but there is ________ in the bowl.","anwers":["no","none","less","any"],"correctAnswer":1},{"category":null,"questionTitle":"The girl you ________ yesterday is waiting for you downstairs.","anwers":["told me","told me about","tell","told me about her"],"correctAnswer":1},{"category":null,"questionTitle":"London is ________ of Englan","anwers":["capital","a capital","an capital","the capital"],"correctAnswer":3},{"category":null,"questionTitle":"Read ________ on the board please.","anwers":["a first sentence","the first sentence","first sentence","sentence first"],"correctAnswer":1}]