[{"category":null,"questionTitle":"Next Tuesday he'll speak to the General Assembly about his world ...........","anwers":["vacation","tour","politics","competition"],"correctAnswer":1},{"category":null,"questionTitle":"His class kept ...................... on the book report last week.","anwers":["talk","to talk","talking","talks"],"correctAnswer":2},{"category":null,"questionTitle":"We couldn't see the moon because there were so many .............","anwers":["stars","surfaces","clouds","atmospheres"],"correctAnswer":2},{"category":null,"questionTitle":"Music was ...................... by the band in May Day marches.","anwers":["taken part","playing","played","play"],"correctAnswer":2},{"category":null,"questionTitle":"How will your brother ............. for living in England?","anwers":["gain","earn","perform","look"],"correctAnswer":1},{"category":null,"questionTitle":"the room cleaned yesterday?","anwers":["Did","Was","Were","Does"],"correctAnswer":1},{"category":null,"questionTitle":"The .......... is the most wonderful invention in the 20th century.","anwers":["furniture","astronaut","machinery","computer"],"correctAnswer":3},{"category":null,"questionTitle":"They are talking about the actress ...................... they saw in the film on TV last night.","anwers":["whose","which","whom","who"],"correctAnswer":2},{"category":null,"questionTitle":"Last Wednesday morning, Bill ....... me up at nine o'clock.","anwers":["shouted","called","rang","b and c are correct"],"correctAnswer":3},{"category":null,"questionTitle":"That's the hall ...................... the meeting will be celebrated .","anwers":["what","where","when","that"],"correctAnswer":1},{"category":null,"questionTitle":"The visiting team has scored a goal from a ........................","anwers":["match","contest","penalty","final"],"correctAnswer":2},{"category":null,"questionTitle":"Sunday is the day ...................... I often go shopping.","anwers":["when","where","which","that"],"correctAnswer":0},{"category":null,"questionTitle":"Can you stop .................. in class?","anwers":["talking","talk","to talk","talked"],"correctAnswer":0},{"category":null,"questionTitle":"A new film ...................... at Le Do cinema last night.","anwers":["is shown","showing","was shown","show"],"correctAnswer":2},{"category":null,"questionTitle":"His clock doesn't work and mine doesn't ............","anwers":["too","neither","so","either"],"correctAnswer":3},{"category":null,"questionTitle":"Last summer holidays were the time ...................... they had a lot of fun.","anwers":["that","when","where","whose"],"correctAnswer":1},{"category":null,"questionTitle":"They are ....................... that they can't buy a bicycle.","anwers":["enough poor","poor enough","so poor","too poor"],"correctAnswer":2},{"category":null,"questionTitle":"Jack loves to read the book ...................... he borrowed from Jean last week.","anwers":["which","it","where","who"],"correctAnswer":0},{"category":null,"questionTitle":"We ...................... go to Water Park if we were in Ho Chi Minh city.","anwers":["will","shall","would","could"],"correctAnswer":2},{"category":null,"questionTitle":"I am not able to go to see Mary with you. I wish I ...................... go.","anwers":["shall","can","could","will"],"correctAnswer":2}]