[{"category":null,"questionTitle":"the teacher always gives(the students) homework.","anwers":["me","them","you"],"correctAnswer":1},{"category":null,"questionTitle":"I am reading the book to (my little sister).","anwers":["her","us","him"],"correctAnswer":0},{"category":null,"questionTitle":"the boys are riding (their bikes).","anwers":["it","them","her"],"correctAnswer":1},{"category":null,"questionTitle":"my father is writing a letter to (John).","anwers":["me","her","him"],"correctAnswer":2},{"category":null,"questionTitle":"I don't know (the answer).","anwers":["she","her","it"],"correctAnswer":2},{"category":null,"questionTitle":"Sally is going to (Anne).","anwers":["her","him","me"],"correctAnswer":0},{"category":null,"questionTitle":"Open (the window), please.","anwers":["it","them","us"],"correctAnswer":0},{"category":null,"questionTitle":"Can you tell (the people) the way to the airport, please?","anwers":["you","them","us"],"correctAnswer":1},{"category":null,"questionTitle":"the books are for (Peter).","anwers":["him","her","you"],"correctAnswer":0},{"category":null,"questionTitle":"Can you help (my sister and me), please?","anwers":["her","me","us"],"correctAnswer":2}]