[{"category":null,"questionTitle":"He ____ be able to help you.","anwers":["may","must","should","will"],"correctAnswer":0},{"category":null,"questionTitle":"She ____ have to sell her car and other belongings to pay her debts.","anwers":["will","will probably","might","would"],"correctAnswer":2},{"category":null,"questionTitle":"Where is Anna? - I don't know. She ____ be at the swimming pool or in the park.","anwers":["could","should","must","has to"],"correctAnswer":0},{"category":null,"questionTitle":"It ____ be as easy as you think.","anwers":["can't","couldn't","might not","must not"],"correctAnswer":2},{"category":null,"questionTitle":"Don't ring the doorbell when you get there. Maria's little baby ____ sleeping.","anwers":["must be","should be","may be","may not be"],"correctAnswer":2},{"category":null,"questionTitle":"How did the robbers get in? - We don't know yet. The old woman ____ to lock the door.","anwers":["might forget","could forget","might have forgotten","must have forgotten"],"correctAnswer":2},{"category":null,"questionTitle":"I called her but there was no answer. She ____ left for New York already.","anwers":["may have","must have","should have","has probably"],"correctAnswer":0},{"category":null,"questionTitle":"When can I see him? ____ come back before six today?","anwers":["May he","Might he","Would he","Is he likely to"],"correctAnswer":3},{"category":null,"questionTitle":"I wonder who wrote that letter. ____ Jim have written it?","anwers":["May","Might","Could","Is it possible that"],"correctAnswer":2},{"category":null,"questionTitle":"He said that he ____ go to Italy in June or July.","anwers":["can","should","might","would"],"correctAnswer":2}]