[{"questionTitle":"Viele junge Mädchen möchten Model werden. ... schaffen es.","answers":["Wenige","Wenigen","Weniges","Wenig"],"correctAnswer":0},{"questionTitle":"Die Kindergartenkinder staunten über den präparierten Dinosaurier. ... weinten.","answers":["Einigen","Einige","Dieses","Die"],"correctAnswer":1},{"questionTitle":"Doris hat rote Flecken am Hals. ... kommen von einer Sonnenallergie.","answers":["Es","Diese","Denen","Das"],"correctAnswer":1},{"questionTitle":"Norbert sucht verzweifelt Pilze im Wald. ... hat Veronika längst schon mitgenommen.","answers":["Diese","Dies","Das","Den"],"correctAnswer":0},{"questionTitle":"Markus schenkte Melanie eine CD mit spanischen Liedern. ... gefielen ihr sehr gut.","answers":["Einiges","Einigen","Einiger","Einige"],"correctAnswer":3},{"questionTitle":"Der Zeitungsausträger lässt die Tür sehr laut ins Schloss fallen. ... ist überall unbeliebt.","answers":["Diesen","Er","Weniger","Dies"],"correctAnswer":1},{"questionTitle":"Heinrich ließ Tanja einen Blumenstrauß schicken. ... nahm sie mit Freude entgegen.","answers":["Dieses","Diesen","Es","Das"],"correctAnswer":1},{"questionTitle":"Das Baby spuckte den Spinat wieder aus. ... schmeckte ihm leider gar nicht.","answers":["Dieser","Diesen","Das","Die"],"correctAnswer":0},{"questionTitle":"Lehrerinnen mögen fast alle ihr Schüler. Mit ... halten sie nach dem Kurs Kontakt.","answers":["vielen","einiges","der","vieler"],"correctAnswer":0},{"questionTitle":"Die Büroangestellten sitzen den ganzen Tag im Büro. ... von ihnen haben Übergewicht.","answers":["Vielen","Viel","Dies","Viele"],"correctAnswer":3}]