[{"questionTitle":"Die ... Bäume gefallen mir im Frühling sehr.","answers":["blühenden","geblühte","blühendes","geblühtes"],"correctAnswer":0},{"questionTitle":"Er kann das ... Kind nicht mehr ertragen. Er ist total empfindlich.","answers":["schreiende","geschrieene","schreiendes","geschrieenes"],"correctAnswer":0},{"questionTitle":"Das ... Fenster muss repariert werden. Es ist sehr kalt in unserem Büro.","answers":["zerbrechende","zerbrechendes","zerbrochenes","zerbrochene"],"correctAnswer":3},{"questionTitle":"Ihr alles ... Freund entschuldigte sich bei ihr.","answers":["bereuter","bereuender","bereuendes","bereutes"],"correctAnswer":1},{"questionTitle":"Der Lokführer konnte den ... Zug nicht rechtzeitig stoppen.","answers":["fahrenden","fahrende","gefahrene","gefahrener"],"correctAnswer":0},{"questionTitle":"Es stellte sich heraus, dass die ... Flüssigkeit giftig war.","answers":["trinkende","trinkender","getrunkener","getrunkene"],"correctAnswer":3},{"questionTitle":"Die ... Mutter wird ins Krankenhaus gebracht.","answers":["gewordene","gewordenes","werdendes","werdende"],"correctAnswer":3},{"questionTitle":"Aus jedem ... Fehler kannst du etwas lernen.","answers":["machenden","machende","gemachter","gemachten"],"correctAnswer":3},{"questionTitle":"Der ... Auftritt musste wegen des Regens verschoben werden.","answers":["angekündigte","ankündigende","ankündigender","angekündigtes"],"correctAnswer":0},{"questionTitle":"Für den ... Programmpunkt gibt es keinen Ersatz.","answers":["ausgefallenen","ausfallendes","ausgefallener","ausfallende"],"correctAnswer":0}]