[{"category":null,"questionTitle":"It's useful when you go to an auction if you're ready with cash in ........","anwers":["pocket","purse","case","hand"],"correctAnswer":3},{"category":null,"questionTitle":"I prefer to deal in ....... cash rather than cheques.","anwers":["solid","hard","real","actual"],"correctAnswer":1},{"category":null,"questionTitle":"Every office has a certain amount of ....... cash to pay for things like tea, coffee or stamps.","anwers":["small","little","tiny","petty"],"correctAnswer":3},{"category":null,"questionTitle":"At the moment we are experiencing some cash ....... problems because little money is coming in.","anwers":["fly","stream","flow","run"],"correctAnswer":2},{"category":null,"questionTitle":"At the casino you can cash ....... your chips at the desk.","anwers":["off","out","up","in"],"correctAnswer":3},{"category":null,"questionTitle":"Whatever she does, she just can't help ....... money.","anwers":["doing","making","massing","creating"],"correctAnswer":1},{"category":null,"questionTitle":"There doesn't seem to be anyone working really hard for the business and yet they all seem to earn ....... money.","anwers":["facile","simple","easy","quick"],"correctAnswer":2},{"category":null,"questionTitle":"If you don't want to use a cheque or postal order, you can always use a money ........","anwers":["order","command","instruction","directive"],"correctAnswer":0},{"category":null,"questionTitle":"Q9 That new invention has been very successful and has proved to be a money ....... for its creator.","anwers":["driver","worker","spinner","turner"],"correctAnswer":2},{"category":null,"questionTitle":"This machine is obviously useless and if I were you I'd get your money ........","anwers":["back","again","return","up"],"correctAnswer":0}]