[{"questionTitle":"Ich habe zum Geburtstag neues Brief ____ geschenkt bekommen.","answers":["schirm","rahmen","papier","spiel"],"correctAnswer":2},{"questionTitle":"Dieser Baum ____ ist so hoch, dass man die Baumkrone kaum von unten sieht.","answers":["rahmen","stamm","spiel","nummer"],"correctAnswer":1},{"questionTitle":"Du musst einmal in deinem Kleider ____ aufräumen.","answers":["schirm","nummer","strahl","schrank"],"correctAnswer":3},{"questionTitle":"Er hat mir einen Bilder ____ für das Gemälde machen lassen.","answers":["strahl","rahmen","papier","tuch"],"correctAnswer":1},{"questionTitle":"Sie wollen ein Computer ____ haben, das spannend und interessant ist.","answers":["papier","schrank","kette","spiel"],"correctAnswer":3},{"questionTitle":"Wenn es regnet, spanne ich meinen Regen ____ auf.","answers":["rahmen","tuch","schirm","kette"],"correctAnswer":2},{"questionTitle":"Im Bad hängt für jeden Gast jeweils ein Hand __________________.","answers":["papier","tuch","schirm","schrank"],"correctAnswer":1},{"questionTitle":"Ihre Hals ____ ist bestimmt sehr wertvoll, da sie aus echten Diamanten besteht.","answers":["schrank","tuch","kette","schirm"],"correctAnswer":2},{"questionTitle":"Könnte ich vielleicht deine Telefon ____ haben, damit ich dich später anrufen kann?","answers":["strahl","nummer","rahmen","kette"],"correctAnswer":1},{"questionTitle":"Der erste Sonnen ____ fällt auf das Dach.","answers":["spiel","nummer","schirm","strahl"],"correctAnswer":3}]