[{"questionTitle":"Es war ... peinlich gewesen, bei der Prüfung plötzlich ein \"Black-out\" zu haben, aber der Prüfer zeigte viel Verständnis für die missliche Lage.","answers":["enorm","halt","ruhig","aber"],"correctAnswer":0},{"questionTitle":"Hans hat versprochen, dass er mit deiner Tochter Mathematik lernt, wenn er wieder ... Zeit hat.","answers":["halt","ja","denn","mal"],"correctAnswer":3},{"questionTitle":"Danke der Nachfrage, Herr Doktor, es geht mir schon wieder ... gut.","answers":["besonders","ziemlich","eigentlich","sogar"],"correctAnswer":1},{"questionTitle":"Stell dir vor: Bei der Party hat ... der Busfahrer Alkohol getrunken!","answers":["halt","mal","eigentlich","sogar"],"correctAnswer":3},{"questionTitle":"Es ist ... ärztlich erwiesen, dass Passivrauchen genauso schädlich ist, wie direktes Rauchen!","answers":["sogar","gar","äußerst","enorm"],"correctAnswer":0},{"questionTitle":"Hast du schon gehört? Sabine ist verliebt in Klaus, weil der ... gut Fußball spielen kann!","answers":["ziemlich","überhaupt","mal","eigentlich"],"correctAnswer":0},{"questionTitle":"Wenn ich Ihnen noch einen Kredit gewähre, begebe ich mich in eine ... prekäre Situation.","answers":["sogar","ziemlich","doch","ja"],"correctAnswer":1},{"questionTitle":"Die Klausuren fielen ... gut aus, jedoch hätte sich der Professor mehr \"Sehr gut\" gewünscht.","answers":["recht","besonders","vielleicht","irre"],"correctAnswer":0},{"questionTitle":"Schlafen Sie ... noch eine Nacht darüber. Es reicht, wenn Sie mich morgen über ihre Entscheidung informieren.","answers":["doch","ja","eigentlich","sehr"],"correctAnswer":0},{"questionTitle":"Angelas Kinder sind ... anstrengend! Und trotzdem möchte sie gerne noch eines!","answers":["gar","enorm","halt","mal"],"correctAnswer":1}]