[{"questionTitle":"Ist das deine Kamera? Ja, aber _______ funktioniert nicht.","answers":["er","sie","ihn","es"],"correctAnswer":1},{"questionTitle":"Ist das Ihr Auto? Ja, aber _______ fährt nicht.","answers":["es","er","ihn","sie"],"correctAnswer":0},{"questionTitle":"Ist das deine Taschenlampe? Ja, aber _______ funktioniert nicht.","answers":["sie (pl)","sie (sg)","es","er"],"correctAnswer":1},{"questionTitle":"Ist das dein Taschenrechner? Ja, aber _______ geht nicht.","answers":["ihn","sie","es","er"],"correctAnswer":3},{"questionTitle":"Sind das Ihre Batterien? Ja, aber _______ sind leer.","answers":["ihr","es","sie(pl)","er"],"correctAnswer":2},{"questionTitle":"Ist das Ihre Uhr? Ja, aber _______ geht nicht.","answers":["sie","es","er","wir"],"correctAnswer":0},{"questionTitle":"Sind das Ihre Kugelschreiber? Ja, aber _______ schreiben nicht.","answers":["euch","er","sie(pl)","es"],"correctAnswer":2},{"questionTitle":"Ist das dein Telefon? Ja, aber _______ geht nicht.","answers":["ihn","er","sie","es"],"correctAnswer":3},{"questionTitle":"Herr Schneider wohnt in München. _______ ist Lehrer","answers":["Es","Er","Ihn","Sie"],"correctAnswer":1},{"questionTitle":"Was studiert ihr? - _______ studieren Jura.","answers":["Ihr","Sie","Wir","Er"],"correctAnswer":2}]