[{"questionTitle":"Nächste Woche _________ wir nicht zum Deutschkurs kommen.","answers":["kannen","können","könnt","kann"],"correctAnswer":1},{"questionTitle":"Letzte Woche _________ mein Sohn seine Diplomarbeit fertig schreiben.","answers":["müsst","muss","musste","musst"],"correctAnswer":2},{"questionTitle":"Der Chef hat gesagt, dass ich diese Rechnungen bis heute Abend schreiben __________ .","answers":["solle","soll","sollt","sollte"],"correctAnswer":1},{"questionTitle":"Entschuldigung, __________ ich Sie etwas fragen?","answers":["dürfe","dürf","darf","dürfen"],"correctAnswer":2},{"questionTitle":"Als ich ein Kind war, _________ ich Astronaut werden.","answers":["will","wolle","woll","wollte"],"correctAnswer":3},{"questionTitle":"__________ du mir helfen, diesen Brief ins Spanische zu übersetzen?","answers":["Kannst","Könntst","Könnt","kann"],"correctAnswer":0},{"questionTitle":"Wenn man Alkohol trinkt, __________ man nicht Auto fahren.","answers":["dürft","dürfe","darf","darft"],"correctAnswer":2},{"questionTitle":"Warum __________ ihr euch jeden Tag streiten?","answers":["musst","müsst","muss","müsstet"],"correctAnswer":1}]