[{"category":null,"questionTitle":"___ book","anwers":["the","Ø","a","an"],"correctAnswer":2},{"category":null,"questionTitle":"___ uniform","anwers":["the","Ø","a","an"],"correctAnswer":2},{"category":null,"questionTitle":"I like ___ tea","anwers":["the","Ø","a","an"],"correctAnswer":1},{"category":null,"questionTitle":"I hate ___ spiders","anwers":["the","Ø","a","an"],"correctAnswer":1},{"category":null,"questionTitle":"Listen to ___ teacher!","anwers":["the","Ø","a","an"],"correctAnswer":0},{"category":null,"questionTitle":"I like ___ dress you bought","anwers":["the","Ø","a","an"],"correctAnswer":0},{"category":null,"questionTitle":"___ United States","anwers":["the","Ø","a","an"],"correctAnswer":0},{"category":null,"questionTitle":"___ United Kingdom","anwers":["the","Ø","a","an"],"correctAnswer":0},{"category":null,"questionTitle":"___ Daltons","anwers":["the","Ø","a","an"],"correctAnswer":0}]