[{"category":null,"questionTitle":"","anwers":["<u><font color='red'>o</font></u>ccasion","<u><font color='red'>o</font></u>dd","<u><font color='red'>o</font></u>ccupy","<u><font color='red'>o</font></u>bvious"],"correctAnswer":0},{"category":null,"questionTitle":"","anwers":["<u><font color='red'>ei</font></u>ght","h<u><font color='red'>ei</font></u>ght","w<u><font color='red'>ei</font></u>ght","w<u><font color='red'>ei</font></u>gh"],"correctAnswer":1},{"category":null,"questionTitle":"","anwers":["t<u><font color='red'>e</font></u>nt","pl<u><font color='red'>e</font></u>nty","<u><font color='red'>e</font></u>nhance","b<u><font color='red'>e</font></u>nd"],"correctAnswer":2},{"category":null,"questionTitle":"","anwers":["b<u><font color='red'>oo</font></u>k","l<u><font color='red'>oo</font></u>k","fl<u><font color='red'>oo</font></u>r","h<u><font color='red'>oo</font></u>k"],"correctAnswer":2},{"category":null,"questionTitle":"","anwers":["h<u><font color='red'>i</font></u>re","f<u><font color='red'>i</font></u>nd","f<u><font color='red'>i</font></u>le","f<u><font color='red'>i</font></u>lm"],"correctAnswer":3},{"category":null,"questionTitle":"","anwers":["h<u><font color='red'>a</font></u>te","f<u><font color='red'>a</font></u>t","c<u><font color='red'>a</font></u>t","b<u><font color='red'>a</font></u>t"],"correctAnswer":0},{"category":null,"questionTitle":"","anwers":["s<u><font color='red'>u</font></u>n","f<u><font color='red'>u</font></u>n","p<u><font color='red'>u</font></u>ll","h<u><font color='red'>u</font></u>nt"],"correctAnswer":2},{"category":null,"questionTitle":"","anwers":["p<u><font color='red'>ar</font></u>don","h<u><font color='red'>ar</font></u>d","p<u><font color='red'>ar</font></u>k","p<u><font color='red'>ar</font></u>ent"],"correctAnswer":3},{"category":null,"questionTitle":"","anwers":["sh<u><font color='red'>ir</font></u>t","f<u><font color='red'>ir</font></u>e","f<u><font color='red'>ir</font></u>st","b<u><font color='red'>ir</font></u>d"],"correctAnswer":1},{"category":null,"questionTitle":"","anwers":["th<u><font color='red'>i</font></u>nk","s<u><font color='red'>i</font></u>gn","r<u><font color='red'>i</font></u>ng","s<u><font color='red'>i</font></u>ng"],"correctAnswer":1},{"category":null,"questionTitle":"","anwers":["f<u><font color='red'>i</font></u>ght","h<u><font color='red'>i</font></u>gh","f<u><font color='red'>i</font></u>gure","br<u><font color='red'>i</font></u>ght"],"correctAnswer":2},{"category":null,"questionTitle":"","anwers":["<u><font color='red'>h</font></u>ouse","<u><font color='red'>h</font></u>our","<u><font color='red'>h</font></u>ow","<u><font color='red'>h</font></u>orse"],"correctAnswer":1},{"category":null,"questionTitle":"","anwers":["arrang<u><font color='red'>ed</font></u>","watch<u><font color='red'>ed</font></u>","wash<u><font color='red'>ed</font></u>","walk<u><font color='red'>ed</font></u>"],"correctAnswer":0},{"category":null,"questionTitle":"","anwers":["l<u><font color='red'>o</font></u>ng","s<u><font color='red'>o</font></u>ng","wr<u><font color='red'>o</font></u>ng","t<u><font color='red'>o</font></u>ngue"],"correctAnswer":3}]