[{"questionTitle":"Als sie von dem Vorfall hörte, ging sie ... zur Polizei und berichtete alles, was sie wusste.","answers":["kopfüber","anders","schnurstracks","nebenbei"],"correctAnswer":2},{"questionTitle":"... bemerkt bist du eine schreckliche Köchin.","answers":["Unbekannterweise","Folgendermaßen","Nebenbei","Stundenweise"],"correctAnswer":2},{"questionTitle":"... muss die Feier für den Nationalratspräsident aussehen:","answers":["Vergebens","Folgendermaßen","Wie","Kopfüber"],"correctAnswer":1},{"questionTitle":"Das Mädchen rannte ... über die Strasse und übersah beinahe das Auto.","answers":["genauso","kopfüber","anders","blindlings"],"correctAnswer":3},{"questionTitle":"Er hatte gemeint, ich könne ihm ... vertrauen, also tat ich es auch.","answers":["stundenweise","gezwungenermaßen","blindlings","eilends"],"correctAnswer":2},{"questionTitle":"Nach den drei erholsamen Urlaubswochen stürzt sich Kevin ... in die Arbeit.","answers":["kopfüber","anders","schnurstracks","nebenbei"],"correctAnswer":0},{"questionTitle":"Das Klassentreffen war wirklich lustig! Ich habe ... alte Freunde wiedergetroffen.","answers":["haufenweise","schnurstracks","eilends","anders"],"correctAnswer":0},{"questionTitle":"... packte die Anwaltssekretärin ihre Habseligkeiten, warf ihrem Chef einen letzten Blick zu und verließ für immer die Kanzlei.","answers":["Nebenhin","Kurzerhand","Insgeheim","Anstandslos"],"correctAnswer":1},{"questionTitle":"Nachdem er lange überlegt hatte, fasste er sich schlussendlich ein Herz, zog sie an sich und küsste sie ... auf den Mund.","answers":["nebenhin","kurzerhand","insgeheim","anstandslos"],"correctAnswer":1},{"questionTitle":"Oh, es tut mir so leid, dass ich nicht kommen kann, aber ich habe noch ... Arbeit zu erledigen.","answers":["rundweg","haufenweise","kurzerhand","anstandslos"],"correctAnswer":1}]