[{"questionTitle":"Nachdem sie alle Streitpunkte geklärt hatten, nahm er tatsächlich ... den Besen und kehrte das Stiegenhaus.","answers":["kurzerhand","anders","unbekannterweise","blindlings"],"correctAnswer":0},{"questionTitle":"... streifte sich Camilla ein altes T-Shirt über, als es plötzlich an der Haustür läutete.","answers":["Anders","Genauso","Flugs","Unbekannterweise"],"correctAnswer":2},{"questionTitle":"Als Popstar laufen einem die Mädchen ... nach! Das muss toll sein!","answers":["rundweg","haufenweise","kurzerhand","anstandslos"],"correctAnswer":1},{"questionTitle":"Neben ihrem Studium arbeitet Sybille ... als Kellnerin in einer kleinen Bar.","answers":["anders","blindlings","eilends","stundenweise"],"correctAnswer":3},{"questionTitle":"Jedes Bemühen war ... . Er war zu sehr gekränkt, um ihr verzeihen zu können.","answers":["kurzerhand","anders","umsonst","genauso"],"correctAnswer":2},{"questionTitle":"Ohje, jetzt war die ganze Arbeit ...! Ich habe aus Versehen alle Dateien gelöscht ohne sie vorher abzuspeichern.","answers":["anders","umsonst","genauso","kurzerhand"],"correctAnswer":1},{"questionTitle":"Es ist nicht nur deine Arbeit schlecht, sondern auch, ... bemerkt, deine Handschrift.","answers":["unbekannterweise","folgendermaßen","nebenbei","stundenweise"],"correctAnswer":2},{"questionTitle":"... bemerkt habe ich deinen Mann heute morgen mit einer Anderen aus einem Hotel kommen sehen.","answers":["Unbekannterweise","Folgendermaßen","Nebenbei","Stundenweise"],"correctAnswer":2},{"questionTitle":"Harrys Mühe, eine gute journalistische Arbeit abzuliefern, war ... Der Verlag kündigte ihm heute morgen.","answers":["anders","umsonst","genauso","kurzerhand"],"correctAnswer":1},{"questionTitle":"Ich will, ... bemerkt, übrigens keine Küchenutensilien mehr zu Weihnachten geschenkt bekommen.","answers":["unbekannterweise","folgendermaßen","nebenbei","stundenweise"],"correctAnswer":2}]