[{"questionTitle":"Infolge der ____ Ernährung ist er krank geworden.","answers":["schlechten","schlechtes","schlechte"],"correctAnswer":0},{"questionTitle":"Laut der ____ Zeitungen hat es 50 Tote gegeben.","answers":["deutscher","deutsche","deutschen"],"correctAnswer":2},{"questionTitle":"Gibt es ein Leben ____ dieses Lebens?","answers":["unweit","wegen","jenseits"],"correctAnswer":2},{"questionTitle":"Ich gehe längs ____ Küste spazieren.","answers":["des","die","der"],"correctAnswer":2},{"questionTitle":"Heutzutage kann man weiße Zähne mittels ____ haben.","answers":["des Lasers","der Laser","das Lasers"],"correctAnswer":0},{"questionTitle":"Der Garten befindet sich ____ des Hauses.","answers":["inmitten","unweit","unterhin"],"correctAnswer":1},{"questionTitle":"____ meiner Krankheit lasse ich mich nicht unterkriegen.","answers":["Wegen","Statt","Trotz"],"correctAnswer":2},{"questionTitle":"Es gibt viele Monumente, die du ____ des Sommerfestes besuchen kannst.","answers":["mittels","anlässlich","oberhalb"],"correctAnswer":1},{"questionTitle":"Wegen ____ trage ich eine Sonnenbrille.","answers":["die Sonne","der Sonne","des Sonnes"],"correctAnswer":1},{"questionTitle":"Die Zollgrenzen ____ der Europäischen Gemeinschaft sind weggefallen.","answers":["ausserhalb","innerhalb","inmittel"],"correctAnswer":1}]