[{"questionTitle":"Eine Fußballmannschaft besteht ____  elf Spielern.","answers":["von","aus","auf"],"correctAnswer":1},{"questionTitle":"Gestern habe ich ____  einem Belote-Turnier teilgenommen.","answers":["in","an","mit"],"correctAnswer":1},{"questionTitle":"Ich bin immer schnell aufgeregt, aber meine Klassennachbarin passt ____  mich auf.","answers":["in","auf","über"],"correctAnswer":1},{"questionTitle":"Ich tausche ____  meinem Freund die Jacke.","answers":["mit","aus","gegen"],"correctAnswer":0},{"questionTitle":"Ich will ____  dem Land wohnen, um ruhiger zu leben.","answers":["auf","in","über"],"correctAnswer":0},{"questionTitle":"Ich denke seit langem oft ____  dich.","answers":["auf","an","von"],"correctAnswer":1},{"questionTitle":"Er ist leider ____  Krebs gestorben.","answers":["an","gegen","über"],"correctAnswer":0},{"questionTitle":"Ich interessiere mich ____  wilde Tiere und die Natur.","answers":["von","für","über"],"correctAnswer":1},{"questionTitle":"Du lachst oft ____  seine dummen Späße.","answers":["auf","von","über"],"correctAnswer":2},{"questionTitle":"Sie fürchtet sich ____  einer kleinen Maus.","answers":["vor","über","von"],"correctAnswer":0}]