[{"category":null,"questionTitle":"________ a car when they were living in London?","anwers":["Have they","Did they have","Were they having","have they had"],"correctAnswer":1},{"category":null,"questionTitle":"They ________ serving meals by the time we get to the restaurant.","anwers":["will stop","stopped","are stopping","will have stopped"],"correctAnswer":3},{"category":null,"questionTitle":"Mark was listening to music while his sister_______ a book.","anwers":["read","reads","is reading","was reading"],"correctAnswer":3},{"category":null,"questionTitle":"You______ here for my party, won't you?","anwers":["shall be","won't be","will be","are going to be"],"correctAnswer":2},{"category":null,"questionTitle":"Can I borrow your bike on Monday? I'm sorry, but_____ it.","anwers":["I'll be using","used","use","have used"],"correctAnswer":0},{"category":null,"questionTitle":"We______ the concert. It was really good.","anwers":["are enjoying","enjoy","did enjoy","would enjoy"],"correctAnswer":2},{"category":null,"questionTitle":"It was 10 p.m. Most of the shops_____ just______","anwers":["have/closed","had/closed","has/closed","was closing"],"correctAnswer":1},{"category":null,"questionTitle":"There's no more apples. We ______ them all.","anwers":["had eaten","ate","eat","have eaten"],"correctAnswer":3},{"category":null,"questionTitle":"She_______ music all day. Now she fells tired.","anwers":["has been playing","is playing","played","plays"],"correctAnswer":0},{"category":null,"questionTitle":"After he________ the house, he wrote a letter.","anwers":["cleans","was cleaning","had cleaned","has cleaned"],"correctAnswer":2}]