[{"questionTitle":"In der Geschwindigkeitsbeschränkungszone fahren die Autos ... langsam.","answers":["entsprechend","entsprechender","entsprechendem","entsprechendes"],"correctAnswer":0},{"questionTitle":"Bei diesem Fachhändler können Sie ihr ... Auto gegen einen Neuwagen eintauschen.","answers":["alte","altes","alten","alt"],"correctAnswer":1},{"questionTitle":"Sieh mal! Mit dieser ... Frau da vorne bin ich in die gleiche Schule gegangen.","answers":["schwangere","schwanger","schwangeren","schwangerer"],"correctAnswer":2},{"questionTitle":"Ich habe mir die ... ..., neue Frauenzeitschrift gleich abonniert.","answers":["monatlich erscheinende","monatliche erscheinend","monatliche erscheinende","monatlich erscheinend"],"correctAnswer":0},{"questionTitle":"Das ... Theater führt heute keine Operette, sondern ein Kindermärchen auf.","answers":["hiesigen","hiesiger","hiesig","hiesige"],"correctAnswer":3},{"questionTitle":"Die Überlebenschancen für die Unfallopfer von der Autobahn sind leider sehr ...","answers":["geringe","gering","geringen","geringes"],"correctAnswer":1},{"questionTitle":"Die Minister haben bestimmt, dass bald ... Geldstrafen für jene verhängt werden, die am Steuer eines Autos mit dem Handy telefonieren.","answers":["höhere","höherem","höheren","höher"],"correctAnswer":0},{"questionTitle":"Die Minister haben bestimmt, dass bald ... Geldstrafen für jene verhängt werden, die am Steuer eines Autos mit dem Handy telefonieren.","answers":["höhere","höheren","höherem","höher"],"correctAnswer":0},{"questionTitle":"Für ... Aufsehen hat heute der Tod eines Fiakerpferdes in der Wiener Innenstadt gesorgt.","answers":["groß","großes","großen","große"],"correctAnswer":1},{"questionTitle":"Der 8-jährige Junge hatte nur ... zusehen können, wie sein Fußball durch das Fenster der Nachbarin segelte.","answers":["tatenloser","tatenlosen","tatenlosem","tatenlos"],"correctAnswer":3}]