[{"questionTitle":"Le chien ==>> ____ Hund ","answers":["die","das","der"],"correctAnswer":2},{"questionTitle":"L'arbre ==>> ____ Baum ","answers":["die","das","der"],"correctAnswer":2},{"questionTitle":"Le numéro ==>> ____ Nummer ","answers":["die","das","der"],"correctAnswer":0},{"questionTitle":"Le pays ==>> ____ Land ","answers":["die","das","der"],"correctAnswer":1},{"questionTitle":"La cabane ==>> ____ Hütte ","answers":["die","das","der"],"correctAnswer":0},{"questionTitle":"La fenêtre ==>> ____ Fenster ","answers":["die","das","der"],"correctAnswer":1},{"questionTitle":"L'ami ==>> ____ Freund ","answers":["die","das","der"],"correctAnswer":2},{"questionTitle":"L'école ==>> ____ Schule ","answers":["die","das","der"],"correctAnswer":0},{"questionTitle":"L'eau ==>> ____ Wasser ","answers":["die","das","der"],"correctAnswer":1},{"questionTitle":"L'image ==>> ____ Bild ","answers":["die","das","der"],"correctAnswer":1}]