[{"questionTitle":"Kann ich dir helfen? Befindest du ... in Schwierigkeiten?","answers":["dir","dich","/","euch"],"correctAnswer":1},{"questionTitle":"Meine Hände sind ganz dreckig. Dann wasch sie ... doch!","answers":["sich","dich","dir","mich"],"correctAnswer":2},{"questionTitle":"Wir begegneten ... zum ersten Mal bei einer Wanderung mit Freunden.","answers":["sich","euch","uns","dich"],"correctAnswer":2},{"questionTitle":"Sie fragte ..., wo Hans so lange blieb.","answers":["mir","dir","sich","euer"],"correctAnswer":2},{"questionTitle":"gehen - über die Möglichkeit - , - zu informieren - Frank und Sabine - zum Jugendamt - einer Adoption - um - sich - .","answers":["Frank und Sabine gehen zum Jugendamt, um sich über die Möglichkeit einer Adoption zu informieren.","Über die Möglichkeit einer Adoption zu informieren sich, Frank und Sabine zum Jugendamt gehen.","Einer Adoption zu informieren sich gehen, Frank und Sabine über die Möglichkeit zum Jugendamt.","Frank und Sabine zum Jugendamt gehen, sich zu informieren über die Möglichkeit einer Adoption."],"correctAnswer":0},{"questionTitle":"sich - von Fertigprodukten - hauptsächlich - er - ernährt - .","answers":["Sich hauptsächlich von Fertigprodukten er ernährt.","Von Fertigprodukten hauptsächlich er ernährt sich.","Hauptsächlich er ernährt sich von Fertigprodukten.","Er ernährt sich hauptsächlich von Fertigprodukten."],"correctAnswer":3},{"questionTitle":"bemüht - so - lange - um die Stelle - ich - habe - mich - .","answers":["So lange um die Stelle ich habe mich bemüht.","Mich um die Stelle habe ich so lange bemüht.","Ich habe mich so lange um die Stelle bemüht.","Bemüht ich habe mich um die Stelle so lange."],"correctAnswer":2},{"questionTitle":"durch ihr Äußeres - nicht - sich - nur - sie - unterscheiden - .","answers":["Unterscheiden sich nicht durch ihr Äußeres nur sie.","Sie unterscheiden sich nicht nur durch ihr Äußeres.","Sich nicht unterscheiden nur durch ihr Äußeres sie.","Durch ihr Äußeres nicht nur sie sich unterscheiden."],"correctAnswer":1},{"questionTitle":"wir - einigen - schließlich - konnten - uns - doch - .","answers":["Einigen doch schließlich wir konnten uns.","Konnten einigen wir doch uns schließlich.","Schließlich konnten wir uns doch einigen.","Wir einigen konnten uns schließlich doch."],"correctAnswer":2},{"questionTitle":"immer - geliebt - in den 20 Jahren - sich haben - ihrer Ehe - sie - .","answers":["Immer sich haben geliebt sie in den 20 Jahren ihrer Ehe.","In den 20 Jahren ihrer Ehe haben sie sich immer geliebt.","Ihrer Ehe sie immer geliebt sich in den 20 Jahren haben.","Haben sich immer geliebt sie in den 20 Jahren ihrer Ehe."],"correctAnswer":1}]