[{"category":null,"questionTitle":"Poison oak generates irritating poisons ____ even if people merely brush against the plants.","anwers":["they can affect people","that can affect people","what can effect people","which do they affect"],"correctAnswer":1},{"category":null,"questionTitle":"____ ants live in colonies, keep farms, go to war, carry off slaves, and have a society somewhat like human beings.","anwers":["Studies of ant life show that","Studies of ant life that","That is studied","That the studies of ant life"],"correctAnswer":0},{"category":null,"questionTitle":"Generic medications are just as ____, and much less expensive.","anwers":["effectively brand-name products","brand-name products effective","brand-name products as effective","effective as brand-name products"],"correctAnswer":3},{"category":null,"questionTitle":"____ is no way to tell the exact number of heroin addicts in the United States.","anwers":["It","There","What","Each"],"correctAnswer":1},{"category":null,"questionTitle":"Ernest Hemingway is ____ of modern fiction.","anwers":["one of the molders","the molders one","who is one of the molders","the molders who is the one"],"correctAnswer":0},{"category":null,"questionTitle":"____ occasions for congratulations.","anwers":["Birthdays that usually considered","Usually considering birthdays","Birthdays are usually considered","That considered birthdays usually"],"correctAnswer":2},{"category":null,"questionTitle":"Forty-niners ____ to California for gold in 1848.","anwers":["rushed","are rushed","have rushed","rushing"],"correctAnswer":0},{"category":null,"questionTitle":"In order for people to work together effectively, they need ____ each other's needs.","anwers":["to be sensitive to","is sensitive for","sensitivity","sensitive"],"correctAnswer":0},{"category":null,"questionTitle":"It is good form to use the name of the person ____.","anwers":["who are greeting","you are greeting","which you are greeting","greeting for you"],"correctAnswer":1},{"category":null,"questionTitle":"____ the promotion of health and to helping people avoid injury and disease.","anwers":["To commit the Red Cross","The Red Cross to commit","Committed to the Red Cross is","The Red Cross is committed to"],"correctAnswer":3},{"category":null,"questionTitle":"People usually can get a sufficient amount of the calcium their bodies ____ from the food they consume.","anwers":["need","needs","needing","to need"],"correctAnswer":0},{"category":null,"questionTitle":"It is possible ____ may assist some trees in saving water in the winter.","anwers":["the leaves are lost","when leaves have lost","that the loss of leaves","to lose leaves"],"correctAnswer":2},{"category":null,"questionTitle":"Hollywood, the heart of America's motion picture industry, ____ of Los Angeles a century ago.","anwers":["was only a quiet suburb","only quiet suburb was","quiet suburb only was","suburb was quiet only"],"correctAnswer":0},{"category":null,"questionTitle":"Kitchen appliances called blenders became ____ in the 1930s, when Stephen J. Poplawski developed a machine that excelled at making his favorite drink.","anwers":["establish","establishing","established","which establish"],"correctAnswer":2},{"category":null,"questionTitle":"Built at the beginning of the century, the Library of Congress houses one of the largest ____ collections of books in the worl","anwers":["and fine","and fineest","or finest","yet fine"],"correctAnswer":1}]