[{"category":null,"questionTitle":"\"This machine doesn't seem to be working.\" \"Try ............ the green button.\"","anwers":["press","to press","pressing","pressed"],"correctAnswer":2},{"category":null,"questionTitle":"Almost every society now has a money economy based .............coins and paper notes of one kind or another.","anwers":["with","in","through","on"],"correctAnswer":3},{"category":null,"questionTitle":"She now regrets having .......... what she said .","anwers":["say","to say","saying","said"],"correctAnswer":3},{"category":null,"questionTitle":"Daisy's interested ............ collecting stamps.","anwers":["for","with","in","on"],"correctAnswer":2},{"category":null,"questionTitle":"I caught the thief ......... into the store.","anwers":["break","to break","breaking","broke"],"correctAnswer":2},{"category":null,"questionTitle":"to go for a trip with my family next weekend?","anwers":["Should you like","Would you like","Will you like","Have you like"],"correctAnswer":1},{"category":null,"questionTitle":"At the crowded places, we often see the sign: \"...................... for pick pockets!\"","anwers":["Watch up","Watch on","Watch out","Watch at"],"correctAnswer":2},{"category":null,"questionTitle":"Did Joe finally go home? No. He ........ going to leave last week, but he lost all his money.","anwers":["must be","was","hasn't been","isn't"],"correctAnswer":1},{"category":null,"questionTitle":"Hurry up! I don't want to risk ............... the train.","anwers":["to miss","missing","missed","miss"],"correctAnswer":1},{"category":null,"questionTitle":"Ricardo didn't remember what I..............him the day before.","anwers":["would tell","had told","had been told","have told"],"correctAnswer":1},{"category":null,"questionTitle":"We get tired of .............. for the bus every morning.","anwers":["wait","to wait","waiting","waited"],"correctAnswer":2},{"category":null,"questionTitle":"It you hadn't reminded me, I ................. your father's death's anniversary.","anwers":["have forgotten","did forget","would have forgotten","will forget"],"correctAnswer":2},{"category":null,"questionTitle":"It is too cold for us .......... swimming.","anwers":["go","to go","going","gone"],"correctAnswer":1},{"category":null,"questionTitle":"No one saw him come in. He came in without..................","anwers":["anybody saw him","anybody sees him","being seen","been seen"],"correctAnswer":2},{"category":null,"questionTitle":"by her mother, Mary went to the circus with Nancy's family.","anwers":["Allow","To allow","Allowing","Allowed"],"correctAnswer":3},{"category":null,"questionTitle":"How long ago..............the Civil War?","anwers":["was","happened","occurred","took place"],"correctAnswer":0},{"category":null,"questionTitle":"Please remember ............. the letter.","anwers":["post","to post","posting","posted"],"correctAnswer":1},{"category":null,"questionTitle":"She was sitting on the park bench when she...............a strange noise.","anwers":["heard","hears","was hearing","had heard"],"correctAnswer":0},{"category":null,"questionTitle":"I enjoyed .............. to folk music.","anwers":["listen","to listen","listening","listened"],"correctAnswer":2}]