[{"questionTitle":"Er lässt sich die Haare ____ schneiden. ","answers":["-","zu"],"correctAnswer":0},{"questionTitle":"Sie sieht den Onkel Benzin ____ tanken. ","answers":["-","zu"],"correctAnswer":0},{"questionTitle":"Wir brauchen uns keine Sorgen ____ machen. ","answers":["-","zu"],"correctAnswer":1},{"questionTitle":"Dieser Lehrer scheint alles ____ wissen. ","answers":["-","zu"],"correctAnswer":1},{"questionTitle":"Er hört die Eltern nach Hause ____ kommen. ","answers":["-","zu"],"correctAnswer":0},{"questionTitle":"Meine Schwester glaubte ihn gut ____ kennen. ","answers":["-","zu"],"correctAnswer":1},{"questionTitle":"Es tut mir leid! Ich kann dir nicht ____ helfen. ","answers":["-","zu"],"correctAnswer":0},{"questionTitle":"Der Landwirt hat noch viel ____ arbeiten. ","answers":["-","zu"],"correctAnswer":1},{"questionTitle":"Sie hofft, das Haus teurer ____ verkaufen. ","answers":["-","zu"],"correctAnswer":1},{"questionTitle":"Wir versuchen, um 9 Uhr ____ kommen. ","answers":["-","zu"],"correctAnswer":1}]