[{"category":null,"questionTitle":"The only way to clean the box is to ________ it in soap and warm water.","anwers":["polish","wash","brush","wipe"],"correctAnswer":1},{"category":null,"questionTitle":"It's ________ to rain again before morning.","anwers":["possibly","likely","probably","certainly"],"correctAnswer":1},{"category":null,"questionTitle":"Little Angela hasn't ________ her shyness yet.","anwers":["got over","got away from","got through","got under"],"correctAnswer":0},{"category":null,"questionTitle":"The garage gave me a 5 per cent ________ for paying cash.","anwers":["discount","bargain","sale","less"],"correctAnswer":0},{"category":null,"questionTitle":"His cheek was very ________ after the wasp stung him.","anwers":["wide","swollen","thick","blown"],"correctAnswer":1},{"category":null,"questionTitle":"________ I have an orange juice, please?","anwers":["Shall","Must","Could","Will"],"correctAnswer":2},{"category":null,"questionTitle":"Trade Union officials and management met today to discuss the ________ at the factory.","anwers":["strike","closing","block","shutting"],"correctAnswer":0},{"category":null,"questionTitle":"She was unable to warn her mother that she would be late because the telephone was ________.","anwers":["out of work","off work","out of order","off duty"],"correctAnswer":2},{"category":null,"questionTitle":"Don't ________ him to arrive early. He's always late.","anwers":["think","judge","attend","expect"],"correctAnswer":3},{"category":null,"questionTitle":"Our teacher explains things so quickly that sometimes I can't ________ her.","anwers":["keep on with","keep at","keep up to","keep up with"],"correctAnswer":3},{"category":null,"questionTitle":"I'm so sorry I'm late, the car broke ________ on my way here.","anwers":["down","up","in","over"],"correctAnswer":0},{"category":null,"questionTitle":"The Prime Minister signed the agreement ________ the British Government.","anwers":["on account of","on behalf of","because of","by means of"],"correctAnswer":1},{"category":null,"questionTitle":"Who is going to pay ________ the damage?","anwers":["on","in","for","to"],"correctAnswer":2},{"category":null,"questionTitle":"George is jealous ________ his younger sister.","anwers":["to","at","from","of"],"correctAnswer":3},{"category":null,"questionTitle":"He might be good ________ his job, but you can't rely on him.","anwers":["in","on","at","by"],"correctAnswer":2},{"category":null,"questionTitle":"He had been completely exhausted but felt considerably ________ after a meal and a rest.","anwers":["renewed","renovated","refreshed","remade"],"correctAnswer":2},{"category":null,"questionTitle":"My eldest brother intends to take ________ skating next winter.","anwers":["to","in","away","up"],"correctAnswer":3},{"category":null,"questionTitle":"The bank ________ planned to escape in a stolen car.","anwers":["thieves","bandits","burglars","robbers"],"correctAnswer":3},{"category":null,"questionTitle":"Which surgeon is ________ this month?","anwers":["on the call","on call","at call","at the call"],"correctAnswer":1},{"category":null,"questionTitle":"Mary was very annoyed that her secretary did not meet her deadlines, and she warned her that her laziness and ________ could result in her dismissal.","anwers":["procrastination","ambition","zeal","fortitude"],"correctAnswer":0}]