[{"category":null,"questionTitle":"The young soldier ________ a dangerous mission across the desert, although he knew that he might be killed.","anwers":["undertook","agreed","promised","entered"],"correctAnswer":0},{"category":null,"questionTitle":"What a lovely dress ________ on.","anwers":["have you","you've got","have you got","do you have"],"correctAnswer":1},{"category":null,"questionTitle":"They have just released a new record called 'Starlight', ________ you must buy.","anwers":["who","what","that","which"],"correctAnswer":3},{"category":null,"questionTitle":"Because nobody admitted breaking the window, the ________ class was kept in after school.","anwers":["all","whole","each","every"],"correctAnswer":1},{"category":null,"questionTitle":"It was a good attempt, but it didn't really come ________, which was a pity.","anwers":["on","in","off","away"],"correctAnswer":2},{"category":null,"questionTitle":"Your marks are poor, ________ I'm afraid you have failed.","anwers":["although","because","however","therefore"],"correctAnswer":3},{"category":null,"questionTitle":"Excuse me, but would you ________ talking a little bit more quietly? We are trying to work.","anwers":["mind","care","object","rather"],"correctAnswer":0},{"category":null,"questionTitle":"The banks seems to have credited my account with $100 in ________.","anwers":["mistake","fortune","error","accident"],"correctAnswer":2},{"category":null,"questionTitle":"You think that's a good idea? I'm sorry, but I don't ________ you at all.","anwers":["agree to","agree with","disagree to","disagree with"],"correctAnswer":1},{"category":null,"questionTitle":"Although this wine is quite cheap, it is very ________.","anwers":["drunk","drinking","drank","drinkable"],"correctAnswer":3},{"category":null,"questionTitle":"Excuse me, do you ________ me bringing my dog into your house?","anwers":["oppose","mind","object","complain"],"correctAnswer":2},{"category":null,"questionTitle":"He has a very ________ temper and often says things he regrets later.","anwers":["angry","quick","warm","fast"],"correctAnswer":1},{"category":null,"questionTitle":"He says he's sorry ________ what he did, so you need not get angry with him.","anwers":["of","from","for","on"],"correctAnswer":2},{"category":null,"questionTitle":"I'm not satisfied ________ your work.","anwers":["to","of","with","at"],"correctAnswer":2},{"category":null,"questionTitle":"I cannot be held responsible ________ other people's mistakes.","anwers":["by","to","from","for"],"correctAnswer":3},{"category":null,"questionTitle":"I will ask him to give me my record back when I ________ him.","anwers":["will see","see","saw","have seen"],"correctAnswer":1},{"category":null,"questionTitle":"I'm afraid my speech may have ________ you as to my true aims.","anwers":["misled","mistaken","misunderstood","miscalculated"],"correctAnswer":0},{"category":null,"questionTitle":"What he told me was a ________ of lies.","anwers":["pack","load","mob","flock"],"correctAnswer":0},{"category":null,"questionTitle":"The death penalty was ________ many years ago in this country.","anwers":["abstained","aborted","abolished","absolved"],"correctAnswer":2},{"category":null,"questionTitle":"Although the language was ________ and considered to be inferior to standard English, Robert Burns wrote his love poetry in the language of the Scots.","anwers":["interpreted","belittled","distinguished","appreciated"],"correctAnswer":1}]