[{"questionTitle":"Morgen, wenn ich das Haus ... ... ..., kann ich mehr zur Finanzierung sagen.","answers":["gesehen haben werde","gesehen sein werde","gesehen habe werden","gesehen bin werden"],"correctAnswer":0},{"questionTitle":"Am Samstag um die Zeit ... ich mein Blind- Date aus dem Internet schon ... ... . Ach, ich bin ja schon so nervös!","answers":["werde getroffen haben","werde getrofft haben","werde getrofft sein","werde getroffen sein"],"correctAnswer":0},{"questionTitle":"Im Juni, wenn ich endlich fertig ... ... ..., gibt es eine große Party.","answers":["studieren haben werden","studieren sein werden","studiert haben werde","studiert sein werde"],"correctAnswer":2},{"questionTitle":"Müller, Sie haben mir versprochen, dass Sie den Bericht bis heute ... ... ...","answers":["geschrieben haben werden","geschrieben sein werden","werden geschrieben sein","haben geschrieben werden"],"correctAnswer":0},{"questionTitle":"In einer Woche ... er den Atlantik mit einem Schlauboot ... ..., erzählt er in einem Interview.","answers":["wird durchkreuzt haben","wird durchkreuzt sein","werden durchkreuzt hat","werden durchkreuzt ist"],"correctAnswer":0},{"questionTitle":"Ich bin mir sicher, dass sie in einer Woche den roten Sportwagen ... ... ...","answers":["gekauft haben wird.","gekauft haben werden.","gekauft sein wird.","gekauft sein werden."],"correctAnswer":0},{"questionTitle":"Es ... sicher wieder ... ...., wenn wir wie jedes Jahr in unserem Wintersportort ankommen.","answers":["wird geschneit hat","wird geschneit ist","wird geschneit haben","wird geschneit sein"],"correctAnswer":2},{"questionTitle":"Bevor Richard ins Flugzeug nach Australien steigt, ... er am Flughafen sicher von der ganzen Familie ... ...","answers":["wird verabschiedet werden.","wird verabschieden werden.","werden verabschieden wird.","werden verabschieden wird."],"correctAnswer":0},{"questionTitle":"Onkel Max, können wir morgen ins Kino gehen, wenn wir brav ... ... ... ?","answers":["aufgegessen haben werden.","aufgegessen sein werden.","werden aufgegessen haben.","werden aufgegessen sein."],"correctAnswer":0},{"questionTitle":"Wenn Sie in diesem Tempo weiterarbeiten, ... Sie mein Auto morgen noch immer nicht ... ...","answers":["werden repariert haben.","werden repariert sein.","sein repariert werden.","haben repariert werden."],"correctAnswer":0}]