[{"questionTitle":"________ macht Rita? – Sie hört Musik.","answers":["Wo","Wie","Was","Wer"],"correctAnswer":2},{"questionTitle":"________ ist es? - Es ist 13 Uhr.","answers":["Wie viel","Wie lange","Wie groß","Wie spät"],"correctAnswer":3},{"questionTitle":"________ ist deine Wohnung? - Sie ist 40 Quadratmeter groß.","answers":["Wie weit","Wie groß","Wie alt","Wie viel"],"correctAnswer":1},{"questionTitle":"________ lernt ihr schon Deutsch? - Seit 2 Jahren.","answers":["Wie lange","Wie alt","Wie groß","Wie spät"],"correctAnswer":0},{"questionTitle":"________ ist das Baby jetzt? - 6 Wochen.","answers":["Wie groß","Wie lange","Wie alt","Wie weit"],"correctAnswer":2},{"questionTitle":"________ ist der Koffer? - 18 kg.","answers":["Wie","Wie schwer","Wie alt","Wie hoch"],"correctAnswer":1},{"questionTitle":"________ ist das Bett? - Es ist bequem. ","answers":["Wie lange","Was","Wie","Wer"],"correctAnswer":2},{"questionTitle":"________ singt er? - Er singt schlecht. Was","answers":["Wo","Wann","Wie"],"correctAnswer":2}]